{
  "metadata": {
    "branch": "main",
    "lastEdited": "11/4/2025"
  },
  "Four Years, Two Co-ops in Summer 2/Fall": {
    "Year 1": {
      "Fall": ["ECON 1115", "ECON 1000", "HIST 1200", "HIST 1201", "MATH 1231"],
      "Spring": ["ECON 1116", "CS 1100"],
      "Summer 1": ["ECON 2315"]
    },
    "Year 2": {
      "Fall": ["ECON 2316", "HIST 2301", "HIST 2302"],
      "Spring": ["ECON 2350", "EESH 2000"]
    },
    "Year 3": {
      "Spring": ["ECON 2560", "ENGW 3315", "ECON 3520"]
    },
    "Year 4": {
      "Spring": ["ECON 4692", "ECON 3470"]
    }
  }
}
