{
  "executionRoleArn": "arn:aws:iam::059561597014:role/ecsTaskExecutionRole",
  "containerDefinitions": [
    {
      "logConfiguration": {
        "logDriver": "awslogs",
        "options": {
          "awslogs-group": "/ecs/graduatenu-api",
          "awslogs-region": "us-east-1",
          "awslogs-stream-prefix": "ecs"
        }
      },
      "portMappings": [
        {
          "hostPort": 3000,
          "protocol": "tcp",
          "containerPort": 3000
        }
      ],
      "cpu": 0,
      "environment": [
        {
          "name": "POSTGRES_HOST",
          "value": "graduatenu-prod.cmknhxcoikji.us-east-1.rds.amazonaws.com"
        },
        {
          "name": "POSTGRES_PASSWORD",
          "value": "graduatenu"
        },
        {
          "name": "POSTGRES_USER",
          "value": "postgres"
        },
        {
          "name": "RAILS_ENV",
          "value": "production"
        },
        {
          "name": "RAILS_LOG_TO_STDOUT",
          "value": "ENABLE"
        },
        {
          "name": "RAILS_MASTER_KEY",
          "value": "e1d7b93b075de2f3cc3a9c69fa97a897"
        }
      ],
      "memoryReservation": 300,
      "volumesFrom": [],
      "image": "059561597014.dkr.ecr.us-east-1.amazonaws.com/graduatenu-rails:b018116",
      "name": "rails"
    }
  ],
  "placementConstraints": [],
  "memory": "1024",
  "taskRoleArn": "arn:aws:iam::059561597014:role/ecsTaskExecutionRole",
  "family": "graduatenu-api",
  "requiresCompatibilities": ["FARGATE"],
  "networkMode": "awsvpc",
  "cpu": "512",
  "volumes": []
}
