{
  "name": "Art History, Minor",
  "metadata": {
    "verified": false,
    "lastEdited": "11/5/2025",
    "branch": "main"
  },
  "totalCreditsRequired": 0,
  "yearVersion": 2021,
  "requirementSections": [
    {
      "type": "SECTION",
      "title": "Required Courses",
      "requirements": [
        {
          "type": "XOM",
          "numCreditsMin": 20,
          "courses": [
            {
              "type": "COURSE",
              "classId": 1100,
              "subject": "ARTH"
            },
            {
              "type": "COURSE",
              "classId": 1110,
              "subject": "ARTH"
            },
            {
              "type": "COURSE",
              "classId": 1111,
              "subject": "ARTH"
            },
            {
              "type": "AND",
              "courses": [
                {
                  "subject": "ARTH",
                  "classId": 1200,
                  "description": "Visual Intelligence",
                  "type": "COURSE"
                },
                {
                  "subject": "ARTH",
                  "classId": 1201,
                  "description": "Recitation for ARTH 1200",
                  "type": "COURSE"
                }
              ]
            },
            {
              "type": "COURSE",
              "classId": 1400,
              "subject": "ARTH"
            },
            {
              "type": "COURSE",
              "classId": 2210,
              "subject": "ARTH"
            },
            {
              "type": "COURSE",
              "classId": 2211,
              "subject": "ARTH"
            },
            {
              "type": "COURSE",
              "classId": 2212,
              "subject": "ARTH"
            },
            {
              "type": "COURSE",
              "classId": 2213,
              "subject": "ARTH"
            },
            {
              "type": "COURSE",
              "classId": 2215,
              "subject": "ARTH"
            },
            {
              "type": "COURSE",
              "classId": 5100,
              "subject": "ARTH"
            },
            {
              "type": "COURSE",
              "classId": 5902,
              "subject": "ARTH"
            },
            {
              "type": "COURSE",
              "classId": 2501,
              "subject": "ARTE"
            }
          ]
        }
      ],
      "minRequirementCount": 1
    }
  ],
  "concentrations": {
    "minOptions": 0,
    "concentrationOptions": []
  }
}
